paperbush/__init__.py
paperbush/exceptions.py
paperbush/lib.py
paperbush/parser.py
paperbush-0.2.0.dist-info/LICENSE
paperbush-0.2.0.dist-info/WHEEL
paperbush-0.2.0.dist-info/METADATA
paperbush-0.2.0.dist-info/RECORD
