Metadata-Version: 2.1
Name: paperbush
Version: 0.2.0
Summary: Super concise argument parsing tool
License: MIT
Author: trag1c
Author-email: trag1cdev@yahoo.com
Requires-Python: >=3.8,<4.0
Classifier: License :: OSI Approved :: MIT License
Classifier: Programming Language :: Python :: 3
Classifier: Programming Language :: Python :: 3.8
Classifier: Programming Language :: Python :: 3.9
Classifier: Programming Language :: Python :: 3.10
Classifier: Programming Language :: Python :: 3.11
